Workbook

Sheet Parámetros
B2: 🖨️ TIENDA PLASTIK Parámetros Globales de Producción
B5: INSUMOS
B6: Filamento PLA — precio por kg | C6: 28234 | D6: Actualizado 2025
B7: Hojas A5 — precio resma 500 hojas | C7: 17844 | D7: Resma 500 hojas
B8: Packaging (caja de cartón) — unitario | C8: 0 | D8: ⚠️ Pendiente de cotizar
B10: EQUIPO · Bambu Lab A1
B11: Costo de adquisición | C11: 1400000
B12: Valor residual | C12: 350000
B13: Vida útil (horas) | C13: 6000
B14: Consumo eléctrico (W) | C14: 260
B15: Mantenimiento anual ($) | C15: 80000
B16: Horas uso anual | C16: 2000
B18: PARÁMETROS GENERALES
B19: Costo kWh (con todos los impuestos) | C19: 303.98
B20: Valor hora mano de obra | C20: 5000
B21: Desperdicio materia prima (%) | C21: 5
B22: Contingencia (%) | C22: 5
B23: Reinversión (%) | C23: 10
B24: Régimen unificado Mendoza (%) | C24: 4
B25: Marketing mensual total ($) | C25: 15000
B26: Unidades estimadas / mes | C26: 20
B28: HORA MÁQUINA (calculada automáticamente)
B29: Depreciación / hora | C29: =(C11-C12)/C13 -> 175
B30: Energía eléctrica / hora | C30: =(C14/1000)*C19 -> 79.0348
B31: Mantenimiento / hora | C31: =C15/C16 -> 40
B32: 💡 COSTO HORA MÁQUINA TOTAL | C32: =C29+C30+C31 -> 294.0348

Sheet 📓 Base A5 (8 discos)
B2: 🖨️ TIENDA PLASTIK · Cuaderno A5 — Modelo Base (8 discos)
B5: A · COMPONENTES IMPRESOS (filamento)
B6: Pieza | C6: Gramos | D6: Tiempo impr. (min) | E6: Costo filamento
B7: Tapa delantera | C7: 60 | D7: 150 | E7: =(C7/1000)*'Parámetros'!C6 -> 1694.04
B8: Tapa trasera | C8: 60 | D8: 150 | E8: =(C8/1000)*'Parámetros'!C6 -> 1694.04
B9: Discos (8 unid.) | C9: 15 | D9: 75 | E9: =(C9/1000)*'Parámetros'!C6 -> 423.51
B10: Subtotal filamento (sin desperdicio) | C10: =SUM(C7:C9) -> 135 | D10: =SUM(D7:D9) -> 375 | E10: =SUM(E7:E9) -> 3811.59
B11: + Desperdicio ('⚙️ Parámetros'!C21 %) | E11: =E10*('Parámetros'!C21/100) -> 190.5795
B12: ✅ Total filamento c/desperdicio | E12: =E10+E11 -> 4002.1695
B14: B · HOJAS
B15: Cantidad de hojas por cuaderno | C15: 80 | D15: → Costo hojas | E15: =(C15/500)*'Parámetros'!C7 -> 2855.04
B17: C · PACKAGING
B18: Costo packaging unitario (desde Parámetros) | E18: ='Parámetros'!C8 -> 0 | F18: ⚠️ Actualizar en Parámetros cuando esté cotizado
B20: D · HORA MÁQUINA (impresión)
B21: Tiempo total de impresión (min) | C21: =D10 -> 375 | D21: → Costo hora máquina | E21: =(C21/60)*'Parámetros'!C32 -> 1837.7175
B23: E · MANO DE OBRA
B24: Tiempo armado (min) | C24: 45
B25: Tiempo gestión (min) | C25: 15
B26: → Costo mano de obra | E26: =((C24+C25)/60)*'Parámetros'!C20 -> 5000
B28: F · MARKETING PRORRATEADO
B29: Marketing mensual / unidades estimadas | E29: ='Parámetros'!C25/'Parámetros'!C26 -> 750
B31: COSTO DE PRODUCCIÓN
B32: A · Filamento (c/desperdicio) | E32: =E12 -> 4002.1695
B33: B · Hojas | E33: =E15 -> 2855.04
B34: C · Packaging | E34: =E18 -> 0
B35: D · Hora máquina (impresión) | E35: =E21 -> 1837.7175
B36: E · Mano de obra | E36: =E26 -> 5000
B37: F · Marketing prorrateado | E37: =E29 -> 750
B38: COSTO DE PRODUCCIÓN TOTAL | E38: =SUM(E32:E37) -> 14444.927
B39: + Contingencia ('⚙️ Parámetros'!C22 %) | E39: =E38*('Parámetros'!C22/100) -> 722.24635
B40: + Reinversión ('⚙️ Parámetros'!C23 %) | E40: =E38*('Parámetros'!C23/100) -> 1444.4927
B41: 💰 COSTO CON PROVISIONES (base de precio) | E41: =E38+E39+E40 -> 16611.666
B43: PRECIOS POR CANAL — precio = costo_prov / (1 − margen − comisión − régimen)
B45: 💬 Venta Directa (IG/WhatsApp)
B46: Margen objetivo (%) | C46: 35
B47: Comisión canal (%) | C47: 6.5
B48: Régimen unificado (desde '⚙️ Parámetros'!C24 %) | C48: ='Parámetros'!C24 -> 4
B49: Denominador (1 − margen − comisión − régimen) | C49: =1-(C46/100)-(C47/100)-(C48/100) -> 0.545
B50: 🏷️ PRECIO SUGERIDO — Venta Directa (IG/WhatsApp) | E50: =IF(C49>0,E41/C49,"⚠️ Rev. márgenes") -> 30480.121
B51: Ganancia neta estimada | E51: =IF(C49>0,E50*(C46/100),"-") -> 10668.042
B53: 🛒 MercadoLibre
B54: Margen objetivo (%) | C54: 35
B55: Comisión canal (%) | C55: 13
B56: Régimen unificado (desde '⚙️ Parámetros'!C24 %) | C56: ='Parámetros'!C24 -> 4
B57: Denominador (1 − margen − comisión − régimen) | C57: =1-(C54/100)-(C55/100)-(C56/100) -> 0.48
B58: 🏷️ PRECIO SUGERIDO — MercadoLibre | E58: =IF(C57>0,E41/C57,"⚠️ Rev. márgenes") -> 34607.638
B59: Ganancia neta estimada | E59: =IF(C57>0,E58*(C54/100),"-") -> 12112.673
B61: 📦 Mayorista (≥10 unidades)
B62: Margen objetivo (%) | C62: 30
B63: Comisión canal (%) | C63: 6.5
B64: Régimen unificado (desde '⚙️ Parámetros'!C24 %) | C64: ='Parámetros'!C24 -> 4
B65: Denominador (1 − margen − comisión − régimen) | C65: =1-(C62/100)-(C63/100)-(C64/100) -> 0.595
B66: 🏷️ PRECIO SUGERIDO — Mayorista (≥10 unidades) | E66: =IF(C65>0,E41/C65,"⚠️ Rev. márgenes") -> 27918.766
B67: Ganancia neta estimada | E67: =IF(C65>0,E66*(C62/100),"-") -> 8375.6299
B69: 🔵 Azul = datos a ingresar | ⚫ Negro = fórmulas automáticas | 🟢 Verde = resultado final | ⚠️ Packaging pendiente
B71: Efectivo
B72: Margen objetivo (%) | C72: 35
B73: Comisión canal (%) | C73: 0
B74: Régimen unificado (desde '⚙️ Parámetros'!C24 %) | C74: 0.04
B75: Denominador (1 − margen − comisión − régimen) | C75: =1-(C72/100)-(C73/100)-(C74/100) -> 0.6496
B76: 🏷️ PRECIO SUGERIDO — Mayorista (≥10 unidades) | E76: =IF(C75>0,E41/C75,"⚠️ Rev. márgenes") -> 25572.146
B77: Ganancia neta estimada | E77: =IF(C75>0,E76*(C72/100),"-") -> 8950.2511

Sheet ➕ Nuevo Modelo
B2: 🖨️ TIENDA PLASTIK · Nuevo Modelo — completar
B3: A · COMPONENTES IMPRESOS (filamento)
B4: Pieza | C4: Gramos | D4: Tiempo impr. (min) | E4: Costo filamento
B5: Tapa delantera | C5: 60 | D5: 150 | E5: =(C5/1000)*'Parámetros'!C6 -> 1694.04
B6: Tapa trasera | C6: 60 | D6: 150 | E6: =(C6/1000)*'Parámetros'!C6 -> 1694.04
B7: Discos (? unid.) | C7: 15 | D7: 75 | E7: =(C7/1000)*'Parámetros'!C6 -> 423.51
B8: Subtotal filamento (sin desperdicio) | C8: =SUM(C5:C7) -> 135 | D8: =SUM(D5:D7) -> 375 | E8: =SUM(E5:E7) -> 3811.59
B9: + Desperdicio ('⚙️ Parámetros'!C21 %) | E9: =E8*('Parámetros'!C21/100) -> 190.5795
B10: ✅ Total filamento c/desperdicio | E10: =E8+E9 -> 4002.1695
B11: B · HOJAS
B12: Cantidad de hojas por cuaderno | C12: 80 | D12: → Costo hojas | E12: =(C12/500)*'Parámetros'!C7 -> 2855.04
B14: C · PACKAGING
B15: Costo packaging unitario (desde Parámetros) | E15: ='Parámetros'!C8 -> 0 | F15: ⚠️ Actualizar en Parámetros cuando esté cotizado
B17: D · HORA MÁQUINA (impresión)
B18: Tiempo total de impresión (min) | C18: =D8 -> 375 | D18: → Costo hora máquina | E18: =(C18/60)*'Parámetros'!C32 -> 1837.7175
B20: E · MANO DE OBRA
B21: Tiempo armado (min) | C21: 45
B22: Tiempo gestión (min) | C22: 15
B23: → Costo mano de obra | E23: =((C21+C22)/60)*'Parámetros'!C20 -> 5000
B25: F · MARKETING PRORRATEADO
B26: Marketing mensual / unidades estimadas | E26: ='Parámetros'!C25/'Parámetros'!C26 -> 750
B28: COSTO DE PRODUCCIÓN
B29: A · Filamento (c/desperdicio) | E29: =E10 -> 4002.1695
B30: B · Hojas | E30: =E12 -> 2855.04
B31: C · Packaging | E31: =E15 -> 0
B32: D · Hora máquina (impresión) | E32: =E18 -> 1837.7175
B33: E · Mano de obra | E33: =E23 -> 5000
B34: F · Marketing prorrateado | E34: =E26 -> 750
B35: COSTO DE PRODUCCIÓN TOTAL | E35: =SUM(E29:E34) -> 14444.927
B36: + Contingencia ('⚙️ Parámetros'!C22 %) | E36: =E35*('Parámetros'!C22/100) -> 722.24635
B37: + Reinversión ('⚙️ Parámetros'!C23 %) | E37: =E35*('Parámetros'!C23/100) -> 1444.4927
B38: 💰 COSTO CON PROVISIONES (base de precio) | E38: =E35+E36+E37 -> 16611.666
B40: PRECIOS POR CANAL — precio = costo_prov / (1 − margen − comisión − régimen)
B42: 💬 Venta Directa (IG/WhatsApp)
B43: Margen objetivo (%) | C43: 35
B44: Comisión canal (%) | C44: 6.5
B45: Régimen unificado (desde '⚙️ Parámetros'!C24 %) | C45: ='Parámetros'!C24 -> 4
B46: Denominador (1 − margen − comisión − régimen) | C46: =1-(C43/100)-(C44/100)-(C45/100) -> 0.545
B47: 🏷️ PRECIO SUGERIDO — Venta Directa (IG/WhatsApp) | E47: =IF(C46>0,E38/C46,"⚠️ Rev. márgenes") -> 30480.121
B48: Ganancia neta estimada | E48: =IF(C46>0,E47*(C43/100),"-") -> 10668.042
B50: 🛒 MercadoLibre
B51: Margen objetivo (%) | C51: 35
B52: Comisión canal (%) | C52: 13
B53: Régimen unificado (desde '⚙️ Parámetros'!C24 %) | C53: ='Parámetros'!C24 -> 4
B54: Denominador (1 − margen − comisión − régimen) | C54: =1-(C51/100)-(C52/100)-(C53/100) -> 0.48
B55: 🏷️ PRECIO SUGERIDO — MercadoLibre | E55: =IF(C54>0,E38/C54,"⚠️ Rev. márgenes") -> 34607.638
B56: Ganancia neta estimada | E56: =IF(C54>0,E55*(C51/100),"-") -> 12112.673
B58: 📦 Mayorista (≥10 unidades)
B59: Margen objetivo (%) | C59: 30
B60: Comisión canal (%) | C60: 6.5
B61: Régimen unificado (desde '⚙️ Parámetros'!C24 %) | C61: ='Parámetros'!C24 -> 4
B62: Denominador (1 − margen − comisión − régimen) | C62: =1-(C59/100)-(C60/100)-(C61/100) -> 0.595
B63: 🏷️ PRECIO SUGERIDO — Mayorista (≥10 unidades) | E63: =IF(C62>0,E38/C62,"⚠️ Rev. márgenes") -> 27918.766
B64: Ganancia neta estimada | E64: =IF(C62>0,E63*(C59/100),"-") -> 8375.6299
B66: 🔵 Azul = datos a ingresar | ⚫ Negro = fórmulas automáticas | 🟢 Verde = resultado final | ⚠️ Packaging pendiente
